roformer/__init__.py
roformer/configuration_roformer.py
roformer/convert_roformer_original_tf_checkpoint_to_pytorch.py
roformer/modeling_roformer.py
roformer/modeling_tf_roformer.py
roformer/tokenization_roformer.py
roformer/tokenization_roformer_fast.py
roformer/tokenization_utils.py
roformer-0.4.3.dist-info/LICENSE
roformer-0.4.3.dist-info/METADATA
roformer-0.4.3.dist-info/WHEEL
roformer-0.4.3.dist-info/top_level.txt
roformer-0.4.3.dist-info/RECORD
