Metadata-Version: 2.1
Name: roformer
Version: 0.4.3
Summary: roformer_pytorch
Home-page: https://github.com/JunnYu/RoFormer_pytorch
Author: Jun Yu
Author-email: 573009727@qq.com
License: Apache 2.0
Keywords: roformer,pytorch,tf2.0
Platform: UNKNOWN
Requires-Dist: transformers (>=4.13.0)
Requires-Dist: rjieba
